wdlviz/__init__.py
wdlviz/__main__.py
wdlviz/_version.py
wdlviz-1.0.0.dist-info/LICENSE
wdlviz-1.0.0.dist-info/METADATA
wdlviz-1.0.0.dist-info/WHEEL
wdlviz-1.0.0.dist-info/entry_points.txt
wdlviz-1.0.0.dist-info/top_level.txt
wdlviz-1.0.0.dist-info/RECORD
