Metadata-Version: 2.1
Name: wdlviz
Version: 1.0.0
Summary: WDL workflow visualization
Project-URL: repository, https://github.com/miniwdl-ext/wdlviz.git
Classifier: Programming Language :: Python :: 3
Classifier: License :: OSI Approved :: MIT License
Classifier: Operating System :: OS Independent
License-File: LICENSE
Requires-Dist: miniwdl
Requires-Dist: graphviz
Provides-Extra: dev
Requires-Dist: build ; extra == 'dev'
Requires-Dist: twine ; extra == 'dev'
Requires-Dist: pre-commit ; extra == 'dev'
Requires-Dist: ruff ; extra == 'dev'
